DESCRIPTION.rst
MANIFEST.in
README.md
setup.cfg
setup.py
testlinkconsole/.coverage
testlinkconsole/testlinkclient.cfg
testlinkconsole/testlinkconsole.log
testlinkconsole/testlinkconsole.py
testlinkconsole/testlinkconsole.pyc
testlinkconsole.egg-info/PKG-INFO
testlinkconsole.egg-info/SOURCES.txt
testlinkconsole.egg-info/dependency_links.txt
testlinkconsole.egg-info/requires.txt
testlinkconsole.egg-info/top_level.txt
testlinkconsole/libs/__init__.py
testlinkconsole/libs/__init__.pyc
testlinkconsole/libs/consoleBase.py
testlinkconsole/libs/consoleBase.pyc
testlinkconsole/libs/iBDTestPlugin.py
testlinkconsole/libs/iBDTestPlugin.pyc
testlinkconsole/libs/iRunnerPlugin.py
testlinkconsole/libs/iRunnerPlugin.pyc
testlinkconsole/plugins/__init__.py
testlinkconsole/plugins/__init__.pyc
testlinkconsole/plugins/bdlocal.py
testlinkconsole/plugins/bdlocal.pyc
testlinkconsole/plugins/bdlocal.yapsy-plugin
testlinkconsole/plugins/behat.py
testlinkconsole/plugins/behat.pyc
testlinkconsole/plugins/behat.yapsy-plugin
testlinkconsole/plugins/behave.py
testlinkconsole/plugins/behave.pyc
testlinkconsole/plugins/behave.yapsy-plugin
testlinkconsole/plugins/ptestlink.py
testlinkconsole/plugins/ptestlink.pyc
testlinkconsole/plugins/ptestlink.yapsy-plugin
testlinkconsole/tests/.coverage
testlinkconsole/tests/__init__.py
testlinkconsole/tests/__init__.pyc
testlinkconsole/tests/testTestLinkConsole.py
testlinkconsole/tests/testTestLinkConsole.pyc
testlinkconsole/tests/libs/__init__.py
testlinkconsole/tests/libs/__init__.pyc
testlinkconsole/tests/libs/testConsoleBase.py
testlinkconsole/tests/libs/testConsoleBase.pyc
testlinkconsole/tests/libs/testIBDTestPlugin.py
testlinkconsole/tests/libs/testIBDTestPlugin.pyc
testlinkconsole/tests/libs/testIRunnerPlugin.py
testlinkconsole/tests/libs/testIRunnerPlugin.pyc
testlinkconsole/tests/plugins/__init__.py
testlinkconsole/tests/plugins/__init__.pyc
testlinkconsole/tests/plugins/testBDLocal.py
testlinkconsole/tests/plugins/testBDLocal.pyc
testlinkconsole/tests/plugins/testBehat.py
testlinkconsole/tests/plugins/testBehat.pyc
testlinkconsole/tests/plugins/testBehave.py
testlinkconsole/tests/plugins/testBehave.pyc
