Metadata-Version: 1.1
Name: testlinkconsole
Version: 0.3
Summary: Testlink Console 
Home-page: https://github.com/chbrun/testlinkconsole
Author: Christophe Brun
Author-email: christophe.brun.cl194@gadz.org
License: BSD
Keywords: console testlink
Platform: UNKNOWN
Classifier: Development Status :: 3 - Alpha
Classifier: Topic :: Utilities
Classifier: License :: OSI Approved :: BSD License
